{
  "id": "FUNCTIONS_G34.CODING_FUNCTIONS_CALL-DEBUGGING.DEBUG_FIX_SEQUENCE.C8-var1",
  "gameType": "maze",
  "topic": "topic-title-coding_functions_call-debugging",
  "level": 8,
  "titleKey": "Challenge.FUNCTIONS_G34.CODING_FUNCTIONS_CALL-DEBUGGING.DEBUG_FIX_SEQUENCE.C8.Title",
  "questTitleKey": "Challenge.FUNCTIONS_G34.CODING_FUNCTIONS_CALL-DEBUGGING.DEBUG_FIX_SEQUENCE.C8.Description",
  "descriptionKey": "Challenge.FUNCTIONS_G34.CODING_FUNCTIONS_CALL-DEBUGGING.DEBUG_FIX_SEQUENCE.C8.Description",
  "translations": {
    "vi": {
      "Challenge.FUNCTIONS_G34.CODING_FUNCTIONS_CALL-DEBUGGING.DEBUG_FIX_SEQUENCE.C8.Title": "Sửa lỗi: Nhặt trước, đi sau",
      "Challenge.FUNCTIONS_G34.CODING_FUNCTIONS_CALL-DEBUGGING.DEBUG_FIX_SEQUENCE.C8.Description": "Các hàm cần thiết đều được viết đúng. Tuy nhiên, chương trình đang cố gắng thu thập vật phẩm trước khi di chuyển đến đó. Hãy sắp xếp lại thứ tự gọi hàm cho đúng.",
      "topic-title-coding_functions_call-debugging": "Gỡ lỗi Lời gọi Hàm"
    },
    "en": {
      "Challenge.FUNCTIONS_G34.CODING_FUNCTIONS_CALL-DEBUGGING.DEBUG_FIX_SEQUENCE.C8.Title": "Debug: Collect Before Move",
      "Challenge.FUNCTIONS_G34.CODING_FUNCTIONS_CALL-DEBUGGING.DEBUG_FIX_SEQUENCE.C8.Description": "The necessary functions are all written correctly. However, the program is trying to collect the item before moving to it. Rearrange the function call order to fix the bug.",
      "topic-title-coding_functions_call-debugging": "Gỡ lỗi Lời gọi Hàm"
    }
  },
  "supportedEditors": [
    "blockly",
    "monaco"
  ],
  "blocklyConfig": {
    "toolbox": {
      "kind": "categoryToolbox",
      "contents": [
        {
          "kind": "category",
          "name": "%{BKY_GAMES_CATEVENTS}",
          "categorystyle": "events_category",
          "contents": [
            {
              "kind": "block",
              "type": "maze_start"
            }
          ]
        },
        {
          "kind": "category",
          "name": "%{BKY_GAMES_CATMOVEMENT}",
          "categorystyle": "movement_category",
          "contents": [
            {
              "kind": "block",
              "type": "maze_moveForward"
            },
            {
              "kind": "block",
              "type": "maze_turn"
            },
            {
              "kind": "block",
              "type": "maze_jump"
            }
          ]
        },
        {
          "kind": "category",
          "name": "%{BKY_GAMES_CATACTIONS}",
          "categorystyle": "actions_category",
          "contents": [
            {
              "kind": "block",
              "type": "maze_collect"
            }
          ]
        },
        {
          "kind": "sep"
        },
        {
          "kind": "category",
          "name": "%{BKY_GAMES_CATPROCEDURES}",
          "custom": "PROCEDURE",
          "categorystyle": "procedure_category"
        }
      ]
    },
    "maxBlocks": 12,
    "startBlocks": "<xml><block type=\"maze_start\" deletable=\"false\" movable=\"false\"><statement name=\"DO\"><block type=\"maze_collect\"><next><block type=\"maze_moveForward\"><next><block type=\"maze_moveForward\"><next><block type=\"maze_moveForward\"><next><block type=\"maze_moveForward\"><next><block type=\"maze_moveForward\" /></next></block></next></block></next></block></next></block></next></block></statement></block></xml>"
  },
  "gameConfig": {
    "type": "maze",
    "renderer": "3d",
    "blocks": [
      {
        "modelKey": "ground.normal",
        "position": {
          "x": 7,
          "y": 0,
          "z": 7
        }
      },
      {
        "modelKey": "ground.normal",
        "position": {
          "x": 8,
          "y": 0,
          "z": 7
        }
      },
      {
        "modelKey": "ground.normal",
        "position": {
          "x": 9,
          "y": 0,
          "z": 7
        }
      },
      {
        "modelKey": "ground.normal",
        "position": {
          "x": 10,
          "y": 0,
          "z": 7
        }
      },
      {
        "modelKey": "ground.normal",
        "position": {
          "x": 11,
          "y": 0,
          "z": 7
        }
      },
      {
        "modelKey": "ground.normal",
        "position": {
          "x": 12,
          "y": 0,
          "z": 7
        }
      }
    ],
    "players": [
      {
        "id": "player1",
        "start": {
          "x": 7,
          "y": 1,
          "z": 7,
          "direction": 1
        }
      }
    ],
    "collectibles": [
      {
        "id": "c1",
        "type": "crystal",
        "position": {
          "x": 11,
          "y": 1,
          "z": 7
        }
      }
    ],
    "interactibles": [],
    "finish": {
      "x": 12,
      "y": 1,
      "z": 7
    }
  },
  "solution": {
    "type": "reach_target",
    "itemGoals": {
      "crystal": 1
    },
    "optimalBlocks": 7,
    "optimalLines": 6,
    "rawActions": [
      "moveForward",
      "moveForward",
      "moveForward",
      "moveForward",
      "collect",
      "moveForward"
    ],
    "structuredSolution": {
      "main": [
        {
          "type": "maze_moveForward"
        },
        {
          "type": "maze_moveForward"
        },
        {
          "type": "maze_moveForward"
        },
        {
          "type": "maze_moveForward"
        },
        {
          "type": "maze_collect"
        },
        {
          "type": "maze_moveForward"
        }
      ],
      "procedures": {}
    },
    "structuredSolution_fixbug_version": {
      "main": [
        {
          "type": "maze_collect"
        },
        {
          "type": "maze_moveForward"
        },
        {
          "type": "maze_moveForward"
        },
        {
          "type": "maze_moveForward"
        },
        {
          "type": "maze_moveForward"
        },
        {
          "type": "maze_moveForward"
        }
      ],
      "procedures": {}
    }
  },
  "sounds": {
    "win": "/assets/maze/win.mp3",
    "fail": "/assets/maze/fail_pegman.mp3"
  }
}