{
  "id": "topic04-20-fixbug-optimization-var1",
  "gameType": "maze",
  "level": 20,
  "titleKey": "Challenge.topic04-20.Title",
  "topic": "topic-title",
  "questTitleKey": "Challenge.topic04-20.Description",
  "descriptionKey": "Challenge.topic04-20.Description",
  "translations": {
    "en": {
      "topic-title": "Variable",
      "Challenge.topic04-20.Title": "Fix: Optimization",
      "Challenge.topic04-20.Description": "The program works but is inefficient. Refactor the code using variables to make it more optimal and use fewer blocks."
    },
    "vi": {
      "topic-title": "Biến",
      "Challenge.topic04-20.Title": "Sửa lỗi: Tối ưu hóa",
      "Challenge.topic04-20.Description": "Chương trình chạy được nhưng không hiệu quả. Hãy tái cấu trúc mã bằng cách sử dụng các biến để tối ưu hơn và dùng ít khối hơn."
    }
  },
  "supportedEditors": [
    "blockly",
    "monaco"
  ],
  "blocklyConfig": {
    "toolbox": {
      "kind": "categoryToolbox",
      "contents": [
        {
          "kind": "category",
          "name": "Events",
          "categorystyle": "procedure_category",
          "contents": [
            {
              "kind": "block",
              "type": "maze_start"
            }
          ]
        },
        {
          "kind": "category",
          "name": "Movement",
          "categorystyle": "turtle_category",
          "contents": [
            {
              "kind": "block",
              "type": "maze_moveForward"
            },
            {
              "kind": "block",
              "type": "maze_jump"
            },
            {
              "kind": "block",
              "type": "maze_turn"
            }
          ]
        },
        {
          "kind": "category",
          "name": "Actions",
          "categorystyle": "pond_category",
          "contents": [
            {
              "kind": "block",
              "type": "maze_collect"
            },
            {
              "kind": "block",
              "type": "maze_toggle_switch"
            }
          ]
        },
        {
          "kind": "category",
          "name": "Logic",
          "categorystyle": "logic_category",
          "contents": [
            {
              "kind": "block",
              "type": "controls_if"
            },
            {
              "kind": "block",
              "type": "logic_compare"
            },
            {
              "kind": "block",
              "type": "logic_operation"
            },
            {
              "kind": "block",
              "type": "logic_negate"
            },
            {
              "kind": "block",
              "type": "logic_boolean"
            },
            {
              "kind": "block",
              "type": "maze_is_path"
            },
            {
              "kind": "block",
              "type": "maze_is_item_present"
            },
            {
              "kind": "block",
              "type": "maze_is_switch_state"
            },
            {
              "kind": "block",
              "type": "maze_at_finish"
            }
          ]
        },
        {
          "kind": "category",
          "name": "Math",
          "categorystyle": "math_category",
          "contents": [
            {
              "kind": "block",
              "type": "math_number"
            },
            {
              "kind": "block",
              "type": "math_arithmetic",
              "inputs": {
                "A": {
                  "shadow": {
                    "type": "math_number",
                    "fields": {
                      "NUM": 1
                    }
                  }
                },
                "B": {
                  "shadow": {
                    "type": "math_number",
                    "fields": {
                      "NUM": 1
                    }
                  }
                }
              }
            }
          ]
        },
        {
          "kind": "sep"
        },
        {
          "kind": "category",
          "name": "%{BKY_GAMES_CATVARIABLES}",
          "custom": "VARIABLE",
          "categorystyle": "variable_category"
        },
        {
          "kind": "category",
          "name": "%{BKY_GAMES_CATPROCEDURES}",
          "custom": "PROCEDURE",
          "categorystyle": "procedure_category"
        }
      ]
    },
    "maxBlocks": 6,
    "startBlocks": "<xml><block type=\"maze_start\" deletable=\"false\" movable=\"false\"><statement name=\"DO\"></statement></block></xml>"
  },
  "gameConfig": {
    "type": "maze",
    "renderer": "3d",
    "blocks": [
      {
        "modelKey": "ground.normal",
        "position": {
          "x": 3,
          "y": 0,
          "z": 1
        }
      },
      {
        "modelKey": "ground.normal",
        "position": {
          "x": 4,
          "y": 0,
          "z": 1
        }
      },
      {
        "modelKey": "ground.normal",
        "position": {
          "x": 5,
          "y": 0,
          "z": 1
        }
      },
      {
        "modelKey": "ground.normal",
        "position": {
          "x": 6,
          "y": 0,
          "z": 1
        }
      },
      {
        "modelKey": "ground.normal",
        "position": {
          "x": 7,
          "y": 0,
          "z": 1
        }
      },
      {
        "modelKey": "ground.normal",
        "position": {
          "x": 8,
          "y": 0,
          "z": 1
        }
      },
      {
        "modelKey": "ground.normal",
        "position": {
          "x": 9,
          "y": 0,
          "z": 1
        }
      },
      {
        "modelKey": "ground.normal",
        "position": {
          "x": 10,
          "y": 0,
          "z": 1
        }
      },
      {
        "modelKey": "ground.normal",
        "position": {
          "x": 11,
          "y": 0,
          "z": 1
        }
      },
      {
        "modelKey": "ground.normal",
        "position": {
          "x": 12,
          "y": 0,
          "z": 1
        }
      },
      {
        "modelKey": "ground.normal",
        "position": {
          "x": 13,
          "y": 0,
          "z": 1
        }
      },
      {
        "modelKey": "ground.normal",
        "position": {
          "x": 14,
          "y": 0,
          "z": 1
        }
      },
      {
        "modelKey": "wall.brick01",
        "position": {
          "x": 13,
          "y": 1,
          "z": 1
        }
      }
    ],
    "players": [
      {
        "id": "player1",
        "start": {
          "x": 3,
          "y": 1,
          "z": 1,
          "direction": 1
        }
      }
    ],
    "collectibles": [
      {
        "id": "c1",
        "type": "crystal",
        "position": {
          "x": 4,
          "y": 1,
          "z": 1
        }
      },
      {
        "id": "c2",
        "type": "crystal",
        "position": {
          "x": 5,
          "y": 1,
          "z": 1
        }
      },
      {
        "id": "c3",
        "type": "crystal",
        "position": {
          "x": 6,
          "y": 1,
          "z": 1
        }
      },
      {
        "id": "c4",
        "type": "crystal",
        "position": {
          "x": 7,
          "y": 1,
          "z": 1
        }
      },
      {
        "id": "c5",
        "type": "crystal",
        "position": {
          "x": 8,
          "y": 1,
          "z": 1
        }
      },
      {
        "id": "c6",
        "type": "crystal",
        "position": {
          "x": 9,
          "y": 1,
          "z": 1
        }
      },
      {
        "id": "c7",
        "type": "crystal",
        "position": {
          "x": 10,
          "y": 1,
          "z": 1
        }
      },
      {
        "id": "c8",
        "type": "crystal",
        "position": {
          "x": 11,
          "y": 1,
          "z": 1
        }
      },
      {
        "id": "c9",
        "type": "crystal",
        "position": {
          "x": 12,
          "y": 1,
          "z": 1
        }
      }
    ],
    "interactibles": [],
    "finish": {
      "x": 14,
      "y": 1,
      "z": 1
    }
  },
  "solution": {
    "type": "reach_target",
    "itemGoals": {
      "crystal": 1,
      "switch": 1
    },
    "optimalBlocks": 1,
    "optimalLines": 0,
    "rawActions": [],
    "structuredSolution": [
      "MAIN PROGRAM:",
      "  On start:"
    ]
  },
  "sounds": {
    "win": "/assets/maze/win.mp3",
    "fail": "/assets/maze/fail_pegman.mp3"
  }
}